[
  {
    "product_id": "L001",
    "product_title": "Dell XPS 13",
    "product_image": "https://www.startech.com.bd/image/cache/catalog/laptop/dell/xps-13-plus-9320/xps-13-plus-9320-01-500x500.webp",
    "category": "laptops",
    "price": 999,
    "description": "Compact, sleek, and powerful laptop with edge-to-edge display.",
    "specification": [
      "13.4-inch FHD+ InfinityEdge display",
      "Intel Core i7-1260P",
      "16GB RAM, 512GB SSD",
      "Intel Iris Xe Graphics",
      "Backlit keyboard"
    ],
    "availability": true,
    "rating": 4.6
  },
  {
    "product_id": "L002",
    "product_title": "Apple MacBook Pro",
    "product_image": "https://www.startech.com.bd/image/cache/catalog/laptop/apple/macbook-pro-m3/macbook-pro-m3-space-gray-01-500x500.webp",
    "category": "laptops",
    "price": 1999,
    "description": "High-performance MacBook Pro with M2 Pro chip.",
    "specification": [
      "14.2-inch Liquid Retina XDR display",
      "Apple M2 Pro chip",
      "16GB RAM, 512GB SSD",
      "10-core CPU, 16-core GPU",
      "Up to 18 hours battery life"
    ],
    "availability": true,
    "rating": 4.9
  },
  {
    "product_id": "L003",
    "product_title": "HP Spectre x360",
    "product_image": "https://storage.googleapis.com/pickaboo-prod/media/catalog/product/cache/90e3b9f4120fc209bf60003e3b0e1323/1/4/14-ef2025na--31-12-23----4.jpg",
    "category": "laptops",
    "price": 1250,
    "description": "Convertible 2-in-1 laptop with a vibrant touch display.",
    "specification": [
      "13.5-inch OLED touch display",
      "Intel Core i7-1260P",
      "16GB RAM, 512GB SSD",
      "Intel Iris Xe Graphics",
      "360-degree hinge design"
    ],
    "availability": true,
    "rating": 4.7
  },
  {
    "product_id": "L004",
    "product_title": "Lenovo ThinkPad X1",
    "product_image": "https://encrypted-tbn0.gstatic.com/images?q=tbn:ANd9GcRTR3lP75p983opQ5i5HYeLhWu6HI14QeMTX4Fqraf0IzHAt_YyvJfhwxc0qfkRY3kQ8Hw&usqp=CAU",
    "category": "laptops",
    "price": 1425,
    "description": "Durable business laptop with outstanding keyboard and performance.",
    "specification": [
      "14-inch WQXGA display",
      "Intel Core i7-1255U",
      "16GB RAM, 1TB SSD",
      "Intel Iris Xe Graphics",
      "Fingerprint reader"
    ],
    "availability": true,
    "rating": 4.8
  },
  {
    "product_id": "L005",
    "product_title": "Acer Swift 3",
    "product_image": "https://www.startech.com.bd/image/cache/catalog/laptop/acer/swift-go-14-sfg14-41-r3fa/swift-go-14-sfg14-41-r3fa-01-500x500.webp",
    "category": "laptops",
    "price": 750,
    "description": "Lightweight laptop with excellent battery life and performance.",
    "specification": [
      "14-inch FHD IPS display",
      "AMD Ryzen 7 5700U",
      "8GB RAM, 512GB SSD",
      "AMD Radeon Graphics",
      "Backlit keyboard"
    ],
    "availability": true,
    "rating": 4.5
  },
  {
    "product_id": "L006",
    "product_title": "Microsoft Surface",
    "product_image": "https://www.startech.com.bd/image/cache/catalog/laptop/microsoft/surface-laptop-5/surface-laptop-5-matte-black-01-500x500.webp",
    "category": "laptops",
    "price": 1100,
    "description": "Stylish and powerful laptop with high-resolution touch display.",
    "specification": [
      "13.5-inch PixelSense touchscreen",
      "Intel Core i5-1135G7",
      "8GB RAM, 512GB SSD",
      "Intel Iris Xe Graphics",
      "Dolby Atmos speakers"
    ],
    "availability": true,
    "rating": 4.6
  },
  {
    "product_id": "L007",
    "product_title": "ASUS ZenBook 14",
    "product_image": "https://www.startech.com.bd/image/cache/catalog/laptop/asus/zenbook-14-oled-ux3405ma/zenbook-14-oled-ux3405ma-foggy-silver-01-228x228.webp",
    "category": "laptops",
    "price": 900,
    "description": "Ultra-slim laptop with a long-lasting battery and powerful performance.",
    "specification": [
      "14-inch FHD NanoEdge display",
      "AMD Ryzen 5 5500U",
      "16GB RAM, 512GB SSD",
      "AMD Radeon Graphics",
      "ErgoLift hinge"
    ],
    "availability": true,
    "rating": 4.6
  },
  {
    "product_id": "P001",
    "product_title": "Samsung Galaxy S23 Ultra",
    "product_image": "https://www.nexus.com.bd/images/detailed/15/Samsung-Galaxy-S23-Ultra-Cream-Smartphone.jpg",
    "category": "phones",
    "price": 1199,
    "description": "Flagship Samsung smartphone with high-end features.",
    "specification": [
      "6.8-inch Dynamic AMOLED 2X",
      "Snapdragon 8 Gen 2",
      "108MP Quad camera",
      "5000mAh battery",
      "S Pen support"
    ],
    "availability": true,
    "rating": 4.7
  },
  {
    "product_id": "P003",
    "product_title": "Google Pixel 7 Pro",
    "product_image": "https://diamu.com.bd/wp-content/uploads/2022/10/Google-Pixel-7-Pro-280x280.png",
    "category": "phones",
    "price": 899,
    "description": "Google's flagship smartphone with advanced AI features.",
    "specification": [
      "6.7-inch QHD+ OLED display",
      "Google Tensor G2 chip",
      "50MP Triple rear camera",
      "5000mAh battery",
      "Face and fingerprint unlock"
    ],
    "availability": true,
    "rating": 4.6
  },
  {
    "product_id": "P004",
    "product_title": "OnePlus 11",
    "product_image": "https://notebookcheck.net/fileadmin/Notebooks/News/_nc3/OnePlus_10T_4.jpg",
    "category": "phones",
    "price": 799,
    "description": "High-performance smartphone with fast charging and sleek design.",
    "specification": [
      "6.7-inch Fluid AMOLED display",
      "Snapdragon 8 Gen 2",
      "50MP Triple rear camera",
      "5000mAh battery with 100W fast charging",
      "OxygenOS based on Android"
    ],
    "availability": true,
    "rating": 4.5
  },
  {
    "product_id": "A001",
    "product_title": "Apple AirPods Pro",
    "product_image": "https://gsmartbd.com/cdn/shop/files/airpods-pro-2nd-generation-02-500x500_8758db45-fcf6-43eb-9992-14fccd8b065c.webp?v=1698492729",
    "category": "accessories",
    "price": 249,
    "description": "Noise-cancelling earbuds with immersive sound.",
    "specification": [
      "Active Noise Cancellation",
      "Adaptive Transparency",
      "Personalized Spatial Audio",
      "MagSafe charging case",
      "Up to 6 hours of listening time"
    ],
    "availability": true,
    "rating": 4.9
  },
  {
    "product_id": "A001",
    "product_title": "Apple AirPods",
    "product_image": "https://executiveample.com/wp-content/uploads/2023/11/Apple-AirPods-Pro-2nd-generation-with-MagSafe-Charging-Case-USB%E2%80%91C4.webp",
    "category": "accessories",
    "price": 249,
    "description": "Noise-cancelling earbuds with immersive sound.",
    "specification": [
      "Active Noise Cancellation",
      "Adaptive Transparency",
      "Personalized Spatial Audio",
      "MagSafe charging case",
      "Up to 6 hours of listening time"
    ],
    "availability": true,
    "rating": 4.9
  },
  {
    "product_id": "A002",
    "product_title": "Sony WH-1000XM5",
    "product_image": "https://fs.npstatic.com/devices/57/2357-w320h320.png",
    "category": "accessories",
    "price": 399,
    "description": "Industry-leading noise-cancelling over-ear headphones.",
    "specification": [
      "Noise Cancelling Pro",
      "Up to 30 hours battery life",
      "Touch sensor controls",
      "Alexa voice control",
      "Quick Attention Mode"
    ],
    "availability": true,
    "rating": 4.8
  },
  {
    "product_id": "A003",
    "product_title": "Samsung Galaxy Buds 2",
    "product_image": "https://brotherselectronicsbd.com/image/cache/catalog/demo/Accessories/Earphone/Samsung/Buds%202%20Pro/Galaxy%20Buds%202%20Pro%20(4)-800x800.jpg",
    "category": "accessories",
    "price": 229,
    "description": "Compact earbuds with high-quality audio and ANC.",
    "specification": [
      "Active Noise Cancellation",
      "Hi-Fi sound quality",
      "3-microphone system",
      "IPX7 water resistance",
      "Wireless charging case"
    ],
    "availability": true,
    "rating": 4.7
  },
  {
    "product_id": "A004",
    "product_title": "Logitech MX Master 3",
    "product_image": "https://techdiversitybd.com/wp-content/uploads/2022/11/Logitech-MX-Master-3S-2.jpg",
    "category": "accessories",
    "price": 99,
    "description": "Advanced ergonomic mouse for productivity.",
    "specification": [
      "Ultra-fast scrolling",
      "Customizable buttons",
      "4000 DPI sensor",
      "Bluetooth and USB receiver",
      "Compatible with multiple devices"
    ],
    "availability": true,
    "rating": 4.6
  },

  {
    "product_id": "SW001",
    "product_title": "Apple Watch Series 8",
    "product_image": "https://adminapi.applegadgetsbd.com/storage/media/large/Apple-Watch-Series-8-GPS+Cellular-Midnight-4171.jpg",
    "category": "smart-watches",
    "price": 399,
    "description": "Advanced smartwatch with health and fitness tracking.",
    "specification": [
      "Always-On Retina display",
      "ECG and blood oxygen monitoring",
      "Water resistant up to 50 meters",
      "Heart rate monitoring",
      "Customizable watch faces"
    ],
    "availability": true,
    "rating": 4.8
  },
  {
    "product_id": "SW002",
    "product_title": "Samsung Galaxy Watch 5",
    "product_image": "https://brotherselectronicsbd.com/image/cache/catalog/demo/Smart%20Watch/Samsung/Watch%205%20Pro/Galaxy%20Watch5%20Pro%20(4)-800x800.jpg",
    "category": "smart-watches",
    "price": 449,
    "description": "Rugged smartwatch with advanced fitness tracking and GPS.",
    "specification": [
      "1.4-inch Super AMOLED display",
      "GPS with track back feature",
      "Heart rate and SpO2 monitoring",
      "Up to 80 hours battery life",
      "Water and dust resistant (IP68)"
    ],
    "availability": true,
    "rating": 4.7
  },
  {
    "product_id": "SW003",
    "product_title": "Garmin Fenix 7",
    "product_image": "https://ph.garmin.com/m/ph/g/products/fenix-7-pro-sapphire-carbongray-cf-lg.jpg",
    "category": "smart-watches",
    "price": 699,
    "description": "High-performance multisport GPS watch for adventurers.",
    "specification": [
      "1.3-inch sunlight-visible display",
      "Built-in GPS and navigation",
      "Heart rate, SpO2, and VO2 max tracking",
      "Up to 18 days battery life",
      "Waterproof up to 100 meters"
    ],
    "availability": true,
    "rating": 4.9
  },
  {
    "product_id": "SW004",
    "product_title": "Fitbit Sense 2",
    "product_image": "https://diamu.com.bd/wp-content/uploads/2022/11/Fitbit-Sense-2-Advanced-Health-and-Fitness-Smartwatch-6-800x800.jpg",
    "category": "smart-watches",
    "price": 299,
    "description": "Smartwatch with stress management and health monitoring.",
    "specification": [
      "1.58-inch AMOLED display",
      "ECG, heart rate, and skin temperature tracking",
      "Built-in GPS",
      "Up to 6 days battery life",
      "Water resistant up to 50 meters"
    ],
    "availability": true,
    "rating": 4.6
  },

  {
    "product_id": "MB001",
    "product_title": "MacBook Air M2",
    "product_image": "https://adminapi.applegadgetsbd.com/storage/media/large/MacBook-Air-M2-15-inch-8-CPU-10-GPU-Midnight-2449.jpg",
    "category": "macbook",
    "price": 1199,
    "description": "Lightweight MacBook with Apple's powerful M2 chip.",
    "specification": [
      "13.6-inch Liquid Retina display",
      "Apple M2 chip",
      "8GB RAM, 256GB SSD",
      "Fanless design",
      "All-day battery life"
    ],
    "availability": true,
    "rating": 4.9
  },
  {
    "product_id": "MB002",
    "product_title": "MacBook Pro 16-inch",
    "product_image": "https://adminapi.applegadgetsbd.com/storage/media/large/3713-12439.jpg",
    "category": "macbook",
    "price": 2499,
    "description": "High-performance MacBook Pro with M2 Max chip for professionals.",
    "specification": [
      "16.2-inch Liquid Retina XDR display",
      "Apple M2 Max chip",
      "32GB RAM, 1TB SSD",
      "10-core CPU, 32-core GPU",
      "Up to 21 hours battery life"
    ],
    "availability": true,
    "rating": 4.8
  },
  {
    "product_id": "MB003",
    "product_title": "MacBook Pro 14-inch",
    "product_image": "https://adminapi.applegadgetsbd.com/storage/media/large/MacBook-Pro-M3-16inch---Silver-3587.jpg",
    "category": "macbook",
    "price": 1999,
    "description": "Compact yet powerful MacBook Pro with M2 Pro chip.",
    "specification": [
      "14.2-inch Liquid Retina XDR display",
      "Apple M2 Pro chip",
      "16GB RAM, 512GB SSD",
      "10-core CPU, 16-core GPU",
      "Up to 18 hours battery life"
    ],
    "availability": true,
    "rating": 4.9
  },
  {
    "product_id": "MB004",
    "product_title": "MacBook Air M1",
    "product_image": "https://adminapi.applegadgetsbd.com/storage/media/large/2543-64161.jpg",
    "category": "macbook",
    "price": 999,
    "description": "Affordable and efficient MacBook Air with M1 chip.",
    "specification": [
      "13.3-inch Retina display",
      "Apple M1 chip",
      "8GB RAM, 256GB SSD",
      "Fanless design",
      "Up to 18 hours battery life"
    ],
    "availability": true,
    "rating": 4.7
  },

  {
    "product_id": "IP001",
    "product_title": "iPhone 14 Pro",
    "product_image": "https://adminapi.applegadgetsbd.com/storage/media/large/iPhone-14-Pro-Deep-Purple-7300.jpg",
    "category": "iphone",
    "price": 999,
    "description": "The latest iPhone with Dynamic Island and Pro camera system.",
    "specification": [
      "6.1-inch Super Retina XDR display",
      "A16 Bionic chip",
      "48MP triple-camera system",
      "Always-On display",
      "Ceramic Shield protection"
    ],
    "availability": true,
    "rating": 4.8
  },
  {
    "product_id": "IP002",
    "product_title": "iPhone 13",
    "product_image": "https://adminapi.applegadgetsbd.com/storage/media/large/3408-30421.jpg",
    "category": "iphone",
    "price": 799,
    "description": "A powerful and affordable iPhone with impressive camera features.",
    "specification": [
      "6.1-inch Super Retina XDR display",
      "A15 Bionic chip",
      "Dual 12MP camera system",
      "5G capability",
      "Up to 19 hours battery life"
    ],
    "availability": true,
    "rating": 4.6
  },
  {
    "product_id": "IP003",
    "product_title": "iPhone SE",
    "product_image": "https://adminapi.applegadgetsbd.com/storage/media/large/5020-41819.jpg",
    "category": "iphone",
    "price": 429,
    "description": "Compact iPhone with powerful performance at an affordable price.",
    "specification": [
      "4.7-inch Retina HD display",
      "A15 Bionic chip",
      "12MP wide camera",
      "Touch ID",
      "Up to 15 hours video playback"
    ],
    "availability": true,
    "rating": 4.4
  },
  {
    "product_id": "IP004",
    "product_title": "iPhone 12 Mini",
    "product_image": "https://adminapi.applegadgetsbd.com/storage/media/large/1543-14471.jpg",
    "category": "iphone",
    "price": 699,
    "description": "Compact yet powerful iPhone with a stunning OLED display.",
    "specification": [
      "5.4-inch Super Retina XDR display",
      "A14 Bionic chip",
      "Dual 12MP camera system",
      "5G capability",
      "MagSafe technology"
    ],
    "availability": true,
    "rating": 4.5
  }
]
